{
  "colors": {
    "primary": {
      "main": "#f0584b",
      "strong": "#9a342d",
      "soft": "#ffdcd6",
      "contrastText": "#FFFFFF"
    },
    "surface": {
      "default": "#f9fcff",
      "control": "#ffffff",
      "canvas": "#eff6fd",
      "navy": "#122237"
    },
    "text": {
      "primary": "#101b29",
      "secondary": "#536272",
      "muted": "#536272",
      "inverse": "#FFFFFF"
    },
    "border": {
      "light": "#e2edf6",
      "main": "#c9d6e2"
    },
    "semantic": {
      "positive": "#006d3a",
      "positiveSoft": "#d0f2dc",
      "negative": "#a81130",
      "negativeSoft": "#ffe1e1",
      "warning": "#765300",
      "warningSoft": "#fff0bf"
    }
  },
  "typography": {
    "fontFamily": {
      "heading": "'Instrument Sans', sans-serif",
      "body": "'Instrument Sans', sans-serif",
      "mono": "'IBM Plex Mono', monospace"
    },
    "fontSize": {
      "xs": "12px",
      "sm": "14px",
      "md": "15px",
      "lg": "18px",
      "xl": "22px",
      "xxl": "30px",
      "hero": "43px"
    },
    "fontWeight": {
      "regular": "400",
      "medium": "500",
      "semibold": "600",
      "bold": "700"
    }
  },
  "spacing": {
    "xxs": "4px",
    "xs": "8px",
    "sm": "12px",
    "md": "16px",
    "lg": "20px",
    "xl": "24px",
    "xxl": "32px"
  },
  "borderRadius": {
    "control": "14px",
    "card": "16px",
    "sheet": "24px",
    "pill": "9999px"
  },
  "shadows": {
    "none": "none",
    "chrome": "0 6px 14px rgba(18, 34, 55, 0.16)",
    "card": "0 8px 14px rgba(18, 34, 55, 0.12)"
  }
}
